montefevents/__init__.py
montefevents/data.py
montefevents/event.py
montefevents/log.py
montefevents/notification.py
montefevents/policy.py
montefevents/renderer.py
montefevents/test/test_data.py
montefevents/test/test_event.py
montefevents/test/test_notification.py
montefevents/test/test_policy.py
montefevents/test/test_rendrer.py
montefevents-0.1.0.data/scripts/montefevents
montefevents-0.1.0.dist-info/DESCRIPTION.rst
montefevents-0.1.0.dist-info/METADATA
montefevents-0.1.0.dist-info/RECORD
montefevents-0.1.0.dist-info/WHEEL
montefevents-0.1.0.dist-info/metadata.json
montefevents-0.1.0.dist-info/top_level.txt
