Metadata-Version: 2.0
Name: montefevents
Version: 0.1.0
Summary: Toolkit to provide automatic (email) notification of the Montefiore unit's seminars
Home-page: https://github.com/jm-begon/montef-events
Author: Jean-Michel Begon
Author-email: jm.begon@gmail.com
License: BSD3
Keywords: utility email notification
Platform: any
Classifier: Development Status :: 4 - Beta
Classifier: Environment :: Console
Classifier: Intended Audience :: Developers
Classifier: Intended Audience :: Science/Research
Classifier: Intended Audience :: Education
Classifier: License :: OSI Approved :: BSD License
Classifier: Operating System :: OS Independent
Classifier: Programming Language :: Python :: 2.7
Classifier: Programming Language :: Python :: 3.5
Classifier: Topic :: Utilities
Requires-Dist: bs4
